ast2000tools/__init__.py
ast2000tools/constants.py
ast2000tools/relativity.py
ast2000tools/shortcuts.py
ast2000tools/solar_system.py
ast2000tools/space_mission.py
ast2000tools/star_population.py
ast2000tools/utils.py
ast2000tools/__pycache__/__init__.cpython-37.pyc
ast2000tools/__pycache__/constants.cpython-37.pyc
ast2000tools/__pycache__/relativity.cpython-37.pyc
ast2000tools/__pycache__/shortcuts.cpython-37.pyc
ast2000tools/__pycache__/solar_system.cpython-37.pyc
ast2000tools/__pycache__/space_mission.cpython-37.pyc
ast2000tools/__pycache__/star_population.cpython-37.pyc
ast2000tools/__pycache__/utils.cpython-37.pyc
ast2000tools-1.7.4.dist-info/METADATA
ast2000tools-1.7.4.dist-info/WHEEL
ast2000tools-1.7.4.dist-info/top_level.txt
ast2000tools-1.7.4.dist-info/RECORD
