Metadata-Version: 2.1
Name: ast2000tools
Version: 1.7.4
Summary: Tools required for the course AST2000 at the University of Oslo.
Home-page: https://lars-frogner.github.io/ast2000tools/
Author: Lars Frogner
Author-email: lars.frogner@astro.uio.no
Classifier: Programming Language :: Python :: 2.7
Classifier: Programming Language :: Python :: 3.5
Classifier: Programming Language :: Python :: 3.6
Classifier: Programming Language :: Python :: 3.7
Classifier: Programming Language :: Python :: 3.8
Classifier: Operating System :: OS Independent
Requires-Python: >=2.7
Requires-Dist: numpy
Requires-Dist: scipy
Requires-Dist: lxml
Requires-Dist: pillow
Requires-Dist: six
Requires-Dist: setuptools ==58.2.0
Requires-Dist: packaging
